pantsbuild.pants.contrib.go-1.30.4-py3.6-nspkg.pth
pants/contrib/go/__init__.py
pants/contrib/go/register.py
pants/contrib/go/target_types.py
pants/contrib/go/subsystems/__init__.py
pants/contrib/go/subsystems/archive_retriever.py
pants/contrib/go/subsystems/fetch_error.py
pants/contrib/go/subsystems/fetcher.py
pants/contrib/go/subsystems/fetcher_factory.py
pants/contrib/go/subsystems/go_distribution.py
pants/contrib/go/subsystems/go_import_meta_tag_reader.py
pants/contrib/go/subsystems/gofmt.py
pants/contrib/go/subsystems/imported_repo.py
pants/contrib/go/subsystems/protoc_gen_go.py
pants/contrib/go/targets/__init__.py
pants/contrib/go/targets/go_binary.py
pants/contrib/go/targets/go_library.py
pants/contrib/go/targets/go_local_source.py
pants/contrib/go/targets/go_protobuf_library.py
pants/contrib/go/targets/go_remote_library.py
pants/contrib/go/targets/go_target.py
pants/contrib/go/targets/go_thrift_library.py
pants/contrib/go/tasks/__init__.py
pants/contrib/go/tasks/go_binary_create.py
pants/contrib/go/tasks/go_binary_fingerprint_strategy.py
pants/contrib/go/tasks/go_buildgen.py
pants/contrib/go/tasks/go_checkstyle.py
pants/contrib/go/tasks/go_compile.py
pants/contrib/go/tasks/go_fetch.py
pants/contrib/go/tasks/go_fmt.py
pants/contrib/go/tasks/go_fmt_task_base.py
pants/contrib/go/tasks/go_go.py
pants/contrib/go/tasks/go_protobuf_gen.py
pants/contrib/go/tasks/go_run.py
pants/contrib/go/tasks/go_task.py
pants/contrib/go/tasks/go_test.py
pants/contrib/go/tasks/go_thrift_gen.py
pants/contrib/go/tasks/go_workspace_task.py
pantsbuild.pants.contrib.go-1.30.4.dist-info/METADATA
pantsbuild.pants.contrib.go-1.30.4.dist-info/RECORD
pantsbuild.pants.contrib.go-1.30.4.dist-info/WHEEL
pantsbuild.pants.contrib.go-1.30.4.dist-info/entry_points.txt
pantsbuild.pants.contrib.go-1.30.4.dist-info/namespace_packages.txt
pantsbuild.pants.contrib.go-1.30.4.dist-info/top_level.txt
pantsbuild.pants.contrib.go-1.30.4.dist-info/zip-safe
